[{"room": ["B302"], "time": ["15:00-16:30"], "period": ["2018/01/08-2018/04/25"], "class_code": "ENGL3102-32122", "year": "3", "instructor": "TANG CHI KIN", "type": "S", "day": {"fr": "false", "mo": "false", "tu": "false", "we": "false", "su": "false", "th": "false", "sa": "true"}, "subject": "ENGLISH VI"}, {"room": ["B302"], "time": ["16:30-18:00"], "period": ["2018/01/08-2018/04/25"], "class_code": "ENGL3102-32122", "year": "3", "instructor": "TANG CHI KIN", "type": "S", "day": {"fr": "false", "mo": "false", "tu": "false", "we": "false", "su": "false", "th": "false", "sa": "true"}, "subject": "ENGLISH VI"}, {"room": ["M608"], "time": ["19:00-20:30"], "period": ["2018/01/08-2018/04/25"], "class_code": "LLAW3120-32122", "year": "3", "instructor": "CHAN CHI BIU", "type": "S", "day": {"fr": "false", "mo": "false", "tu": "false", "we": "true", "su": "false", "th": "false", "sa": "false"}, "subject": "PUBLIC RELATIONS LAW"}, {"room": ["M608"], "time": ["20:30-22:00"], "period": ["2018/01/08-2018/04/25"], "class_code": "LLAW3120-32122", "year": "3", "instructor": "CHAN CHI BIU", "type": "S", "day": {"fr": "false", "mo": "false", "tu": "false", "we": "true", "su": "false", "th": "false", "sa": "false"}, "subject": "PUBLIC RELATIONS LAW"}, {"room": ["M608"], "time": ["19:00-20:30"], "period": ["2018/01/08-2018/04/25"], "class_code": "MRKT3130-32122", "year": "3", "instructor": "JOYCE TAM FUNG YI", "type": "S", "day": {"fr": "false", "mo": "false", "tu": "false", "we": "false", "su": "false", "th": "true", "sa": "false"}, "subject": "DIRECT MARKETING"}, {"room": ["M608"], "time": ["20:30-22:00"], "period": ["2018/01/08-2018/04/25"], "class_code": "MRKT3130-32122", "year": "3", "instructor": "JOYCE TAM FUNG YI", "type": "S", "day": {"fr": "false", "mo": "false", "tu": "false", "we": "false", "su": "false", "th": "true", "sa": "false"}, "subject": "DIRECT MARKETING"}, {"room": ["B307"], "time": ["15:00-16:30"], "period": ["2018/01/08-2018/04/25"], "class_code": "MRKT3170-32422", "year": "3", "instructor": "TAM SHUK HAN SALLY", "type": "S", "day": {"fr": "false", "mo": "false", "tu": "false", "we": "false", "su": "false", "th": "false", "sa": "true"}, "subject": "CUSTOMER RELATIONSHIP MANAGEMENT"}, {"room": ["B307"], "time": ["16:30-18:00"], "period": ["2018/01/08-2018/04/25"], "class_code": "MRKT3170-32422", "year": "3", "instructor": "TAM SHUK HAN SALLY", "type": "S", "day": {"fr": "false", "mo": "false", "tu": "false", "we": "false", "su": "false", "th": "false", "sa": "true"}, "subject": "CUSTOMER RELATIONSHIP MANAGEMENT"}, {"room": ["M610"], "time": ["19:00-20:30"], "period": ["2018/01/08-2018/04/25"], "class_code": "RPUR3120-32122", "year": "3", "instructor": "LUNG WING YI JANE", "type": "S", "day": {"fr": "false", "mo": "true", "tu": "false", "we": "false", "su": "false", "th": "false", "sa": "false"}, "subject": "PUBLIC RELATIONS AND MARKETING RESEARCH"}, {"room": ["M610"], "time": ["20:30-22:00"], "period": ["2018/01/08-2018/04/25"], "class_code": "RPUR3120-32122", "year": "3", "instructor": "LUNG WING YI JANE", "type": "S", "day": {"fr": "false", "mo": "true", "tu": "false", "we": "false", "su": "false", "th": "false", "sa": "false"}, "subject": "PUBLIC RELATIONS AND MARKETING RESEARCH"}, {"room": ["M612"], "time": ["19:00-20:30"], "period": ["2018/01/08-2018/04/25"], "class_code": "RPUR3140-32122", "year": "3", "instructor": "ERIC CHAO KENG KUAI", "type": "S", "day": {"fr": "true", "mo": "false", "tu": "false", "we": "false", "su": "false", "th": "false", "sa": "false"}, "subject": "MEDIA PLANNING"}, {"room": ["M612"], "time": ["20:30-22:00"], "period": ["2018/01/08-2018/04/25"], "class_code": "RPUR3140-32122", "year": "3", "instructor": "ERIC CHAO KENG KUAI", "type": "S", "day": {"fr": "true", "mo": "false", "tu": "false", "we": "false", "su": "false", "th": "false", "sa": "false"}, "subject": "MEDIA PLANNING"}, {"room": ["B108"], "time": ["19:00-20:30"], "period": ["2018/01/08-2018/04/25"], "class_code": "RPUR3170-32122", "year": "3", "instructor": "ELISA PACK JON FONG RENDALL MONTEIRO", "type": "S", "day": {"fr": "false", "mo": "false", "tu": "true", "we": "false", "su": "false", "th": "false", "sa": "false"}, "subject": "PUBLIC RELATIONS IN THE GLOBAL ENVIRONMENT"}, {"room": ["B108"], "time": ["20:30-22:00"], "period": ["2018/01/08-2018/04/25"], "class_code": "RPUR3170-32122", "year": "3", "instructor": "ELISA PACK JON FONG RENDALL MONTEIRO", "type": "S", "day": {"fr": "false", "mo": "false", "tu": "true", "we": "false", "su": "false", "th": "false", "sa": "false"}, "subject": "PUBLIC RELATIONS IN THE GLOBAL ENVIRONMENT"}]