[{"room": ["A301"], "time": ["14:30-17:30"], "period": ["2019/01/07-2019/04/23"], "class_code": "CHIN3120-32171", "year": "3", "instructor": "TBA", "type": "S", "day": {"fr": "true", "mo": "false", "tu": "false", "we": "false", "su": "false", "th": "false", "sa": "false"}, "subject": "INTRODUCTION TO CHINESE CULTURE"}, {"room": ["A111"], "time": ["10:00-13:00"], "period": ["2019/01/07-2019/04/23"], "class_code": "CHIN3122-32171", "year": "3", "instructor": "JULIA ZHU YING", "type": "S", "day": {"fr": "true", "mo": "false", "tu": "false", "we": "false", "su": "false", "th": "false", "sa": "false"}, "subject": "FOREIGN LITERATURE II"}, {"room": ["P117(\u9ad4\u80b2\u9928) P117"], "time": ["14:30-16:30"], "period": ["2019/01/07-2019/04/23"], "class_code": "CHIN3124-32171", "year": "3", "instructor": "ZHOU JIAN", "type": "S", "day": {"fr": "false", "mo": "false", "tu": "true", "we": "false", "su": "false", "th": "false", "sa": "false"}, "subject": "HISTORY OF CHINESE"}, {"room": ["A310"], "time": ["10:00-13:00"], "period": ["2019/01/07-2019/04/23"], "class_code": "CHIN3126-32171", "year": "3", "instructor": "CHEN ZHIXIONG", "type": "S", "day": {"fr": "false", "mo": "false", "tu": "true", "we": "false", "su": "false", "th": "false", "sa": "false"}, "subject": "GUIDED READING OF CHINESE CLASSICS"}, {"info": "\u7531\u8b1b\u5e2b\u5b89\u6392 To be arranged by lecturers", "class_code": "EDUC3102-32171", "year": "3", "instructor": "LAI SIO IENG", "type": "S", "subject": "TEACHING FIELDWORK II"}, {"room": ["A309"], "time": ["14:30-16:30"], "period": ["2019/01/07-2019/04/23"], "class_code": "EDUC3104-32171", "year": "3", "instructor": "ZHANG HONGFENG", "type": "S", "day": {"fr": "false", "mo": "true", "tu": "false", "we": "false", "su": "false", "th": "false", "sa": "false"}, "subject": "DESIGN AND PRACTICE OF INTERNATIONAL CHINESE TEACHING"}, {"room": ["A108"], "time": ["09:00-11:00"], "period": ["2019/01/07-2019/04/23"], "class_code": "ENGL3116-32171", "year": "3", "instructor": "JOANNE LAU NGAR WAI", "type": "S", "day": {"fr": "false", "mo": "true", "tu": "false", "we": "false", "su": "false", "th": "false", "sa": "false"}, "subject": "ADVANCED ENGLISH IV"}, {"room": ["B103"], "time": ["11:00-13:00"], "period": ["2019/01/07-2019/04/23"], "class_code": "PORT3118-32171", "year": "3", "instructor": "NG CEN ANA", "type": "S", "day": {"fr": "false", "mo": "true", "tu": "false", "we": "false", "su": "false", "th": "false", "sa": "false"}, "subject": "ADVANCED PORTUGUESE II"}, {"room": ["A317"], "time": ["11:00-13:00"], "period": ["2019/01/07-2019/04/23"], "class_code": "PORT3118-32171", "year": "3", "instructor": "NG CEN ANA", "type": "S", "day": {"fr": "false", "mo": "false", "tu": "false", "we": "true", "su": "false", "th": "false", "sa": "false"}, "subject": "ADVANCED PORTUGUESE II"}]