[{"room": ["B307"], "time": ["20:30-23:30"], "period": ["2018/08/27-2018/12/01"], "class_code": "CHIN2101-21442", "year": "2", "instructor": "LAI SIO IENG", "type": "S", "day": {"fr": "false", "mo": "true", "tu": "false", "we": "false", "su": "false", "th": "false", "sa": "false"}, "subject": "CHINESE WRITING"}, {"room": ["B307"], "time": ["18:30-20:30"], "period": ["2018/08/27-2018/12/01"], "class_code": "ENGL2101-21342", "year": "2", "instructor": "JOANNE LAU NGAR WAI", "type": "S", "day": {"fr": "false", "mo": "true", "tu": "false", "we": "false", "su": "false", "th": "false", "sa": "false"}, "subject": "ENGLISH III"}, {"room": ["B307"], "time": ["20:30-22:30"], "period": ["2018/08/27-2018/12/01"], "class_code": "ENGL2101-21342", "year": "2", "instructor": "JOANNE LAU NGAR WAI", "type": "S", "day": {"fr": "false", "mo": "false", "tu": "false", "we": "false", "su": "false", "th": "true", "sa": "false"}, "subject": "ENGLISH III"}, {"room": ["B307"], "time": ["18:30-20:30"], "period": ["2018/08/27-2018/12/01"], "class_code": "ENGL2104-21342", "year": "2", "instructor": "LIANG YAN", "type": "S", "day": {"fr": "false", "mo": "false", "tu": "false", "we": "true", "su": "false", "th": "false", "sa": "false"}, "subject": "ENGLISH PRACTICAL WRITING"}, {"room": ["B307"], "time": ["18:30-20:30"], "period": ["2018/08/27-2018/12/01"], "class_code": "ENGL2105-21342", "year": "2", "instructor": "EDWARD S MITCHELL", "type": "S", "day": {"fr": "false", "mo": "false", "tu": "true", "we": "false", "su": "false", "th": "false", "sa": "false"}, "subject": "APPLIED LINGUISTICS I"}, {"room": ["B307"], "time": ["20:30-22:30"], "period": ["2018/08/27-2018/12/01"], "class_code": "ENGL2107-21342", "year": "2", "instructor": "NG KA IAN", "type": "S", "day": {"fr": "false", "mo": "false", "tu": "true", "we": "false", "su": "false", "th": "false", "sa": "false"}, "subject": "PUBLIC SPEAKING AND DEBATING IN ENGLISH"}, {"room": ["A307"], "time": ["18:30-20:30"], "period": ["2018/08/27-2018/12/01"], "class_code": "FREN2111-21342", "year": "2", "instructor": "TBA", "type": "S", "day": {"fr": "true", "mo": "false", "tu": "false", "we": "false", "su": "false", "th": "false", "sa": "false"}, "subject": "FRENCH I"}, {"room": ["B103"], "time": ["20:30-22:30"], "period": ["2018/08/27-2018/12/01"], "class_code": "HIST2103-21342", "year": "2", "instructor": "DAVID JAMES MELHUISH", "type": "S", "day": {"fr": "false", "mo": "false", "tu": "true", "we": "false", "su": "false", "th": "false", "sa": "false"}, "subject": "BRITISH SOCIETY AND CULTURE"}, {"room": ["B307"], "time": ["18:30-20:30"], "period": ["2018/08/27-2018/12/01"], "class_code": "PORT2111-21342", "year": "2", "instructor": "MILENA SUN YE", "type": "S", "day": {"fr": "true", "mo": "false", "tu": "false", "we": "false", "su": "false", "th": "false", "sa": "false"}, "subject": "PORTUGUESE I"}, {"room": ["B307"], "time": ["20:30-22:30"], "period": ["2018/08/27-2018/12/01"], "class_code": "TRAN2102-21342", "year": "2", "instructor": "CHE WUN CHENG", "type": "S", "day": {"fr": "false", "mo": "false", "tu": "false", "we": "true", "su": "false", "th": "false", "sa": "false"}, "subject": "GENERAL TRANSLATION (E-C)"}, {"room": ["B307"], "time": ["18:30-20:30"], "period": ["2018/08/27-2018/12/01"], "class_code": "TRAN2102-21342", "year": "2", "instructor": "CHE WUN CHENG", "type": "S", "day": {"fr": "false", "mo": "false", "tu": "false", "we": "false", "su": "false", "th": "true", "sa": "false"}, "subject": "GENERAL TRANSLATION (E-C)"}]