[{"room": ["A301"], "time": ["14:15-15:45"], "period": ["2018/08/27-2018/12/01"], "class_code": "BUSS1120-31221", "year": "3", "instructor": "CHOI CHUNG MAN", "type": "S", "day": {"fr": "false", "mo": "false", "tu": "false", "we": "false", "su": "false", "th": "false", "sa": "true"}, "subject": "BUSINESS ETHICS"}, {"room": ["A301"], "time": ["16:00-17:30"], "period": ["2018/08/27-2018/12/01"], "class_code": "BUSS1120-31221", "year": "3", "instructor": "CHOI CHUNG MAN", "type": "S", "day": {"fr": "false", "mo": "false", "tu": "false", "we": "false", "su": "false", "th": "false", "sa": "true"}, "subject": "BUSINESS ETHICS"}, {"room": ["B307"], "time": ["09:00-10:30"], "period": ["2018/08/27-2018/12/01"], "class_code": "ENGL3101-31C21", "year": "3", "instructor": "SARAH IP WAI SA", "type": "S", "day": {"fr": "false", "mo": "false", "tu": "false", "we": "false", "su": "false", "th": "true", "sa": "false"}, "subject": "ENGLISH V"}, {"room": ["B307"], "time": ["10:45-12:15"], "period": ["2018/08/27-2018/12/01"], "class_code": "ENGL3101-31C21", "year": "3", "instructor": "SARAH IP WAI SA", "type": "S", "day": {"fr": "false", "mo": "false", "tu": "false", "we": "false", "su": "false", "th": "true", "sa": "false"}, "subject": "ENGLISH V"}, {"room": ["B306"], "time": ["14:15-15:45"], "period": ["2018/08/27-2018/12/01"], "class_code": "MATH2100-31321", "year": "3", "instructor": "NATALIE PANG WENG SUN", "type": "S", "day": {"fr": "false", "mo": "true", "tu": "false", "we": "false", "su": "false", "th": "false", "sa": "false"}, "subject": "BUSINESS MATHEMATICS"}, {"room": ["B306"], "time": ["16:00-17:30"], "period": ["2018/08/27-2018/12/01"], "class_code": "MATH2100-31321", "year": "3", "instructor": "NATALIE PANG WENG SUN", "type": "S", "day": {"fr": "false", "mo": "true", "tu": "false", "we": "false", "su": "false", "th": "false", "sa": "false"}, "subject": "BUSINESS MATHEMATICS"}, {"room": ["B302"], "time": ["14:15-15:45"], "period": ["2018/08/27-2018/12/01"], "class_code": "MMIS0140-31121", "year": "3", "instructor": "LAI KAM WING COLIN", "type": "S", "day": {"fr": "false", "mo": "false", "tu": "true", "we": "false", "su": "false", "th": "false", "sa": "false"}, "subject": "MANAGEMENT INFORMATION SYSTEMS"}, {"room": ["B302"], "time": ["16:00-17:30"], "period": ["2018/08/27-2018/12/01"], "class_code": "MMIS0140-31121", "year": "3", "instructor": "LAI KAM WING COLIN", "type": "S", "day": {"fr": "false", "mo": "false", "tu": "true", "we": "false", "su": "false", "th": "false", "sa": "false"}, "subject": "MANAGEMENT INFORMATION SYSTEMS"}, {"room": ["B305"], "time": ["14:15-15:45"], "period": ["2018/08/27-2018/12/01"], "class_code": "MRKT0141-31121", "year": "3", "instructor": "MARGARET TANG NGAN FUNG", "type": "S", "day": {"fr": "false", "mo": "false", "tu": "false", "we": "false", "su": "false", "th": "true", "sa": "false"}, "subject": "BUSINESS TO BUSINESS MARKETING"}, {"room": ["B305"], "time": ["16:00-17:30"], "period": ["2018/08/27-2018/12/01"], "class_code": "MRKT0141-31121", "year": "3", "instructor": "MARGARET TANG NGAN FUNG", "type": "S", "day": {"fr": "false", "mo": "false", "tu": "false", "we": "false", "su": "false", "th": "true", "sa": "false"}, "subject": "BUSINESS TO BUSINESS MARKETING"}, {"room": ["B103"], "time": ["09:00-10:30"], "period": ["2018/08/27-2018/12/01"], "class_code": "MRKT3120-31121", "year": "3", "instructor": "CHAN IN", "type": "S", "day": {"fr": "false", "mo": "false", "tu": "false", "we": "false", "su": "false", "th": "false", "sa": "true"}, "subject": "RETAIL MANAGEMENT"}, {"room": ["B103"], "time": ["10:45-12:15"], "period": ["2018/08/27-2018/12/01"], "class_code": "MRKT3120-31121", "year": "3", "instructor": "CHAN IN", "type": "S", "day": {"fr": "false", "mo": "false", "tu": "false", "we": "false", "su": "false", "th": "false", "sa": "true"}, "subject": "RETAIL MANAGEMENT"}, {"room": ["B103"], "time": ["09:00-10:30"], "period": ["2018/08/27-2018/12/01"], "class_code": "MRKT3140-31121", "year": "3", "instructor": "LARRY LEI I SUN", "type": "S", "day": {"fr": "false", "mo": "false", "tu": "false", "we": "true", "su": "false", "th": "false", "sa": "false"}, "subject": "ADVERTISING AND PROMOTION"}, {"room": ["B103"], "time": ["10:45-12:15"], "period": ["2018/08/27-2018/12/01"], "class_code": "MRKT3140-31121", "year": "3", "instructor": "LARRY LEI I SUN", "type": "S", "day": {"fr": "false", "mo": "false", "tu": "false", "we": "true", "su": "false", "th": "false", "sa": "false"}, "subject": "ADVERTISING AND PROMOTION"}, {"room": ["B108"], "time": ["09:00-10:30"], "period": ["2018/08/27-2018/12/01"], "class_code": "MRKT3160-31121", "year": "3", "instructor": "ALBE NG SIO WANG", "type": "S", "day": {"fr": "false", "mo": "false", "tu": "true", "we": "false", "su": "false", "th": "false", "sa": "false"}, "subject": "MARKETING RESEARCH"}, {"room": ["B108"], "time": ["10:45-12:15"], "period": ["2018/08/27-2018/12/01"], "class_code": "MRKT3160-31121", "year": "3", "instructor": "ALBE NG SIO WANG", "type": "S", "day": {"fr": "false", "mo": "false", "tu": "true", "we": "false", "su": "false", "th": "false", "sa": "false"}, "subject": "MARKETING RESEARCH"}]